README.md
setup.py
validator_decorator/__init__.py
validator_decorator/validator.py
validator_decorator.egg-info/PKG-INFO
validator_decorator.egg-info/SOURCES.txt
validator_decorator.egg-info/dependency_links.txt
validator_decorator.egg-info/top_level.txt