Metadata-Version: 2.1
Name: validator-decorator
Version: 0.0.1
Summary: a samll decorator validator for cerberus
Home-page: https://github.com/huaSoftware/chat
Author: Dejecte Programmer
Author-email: 584425439@qq.com
License: UNKNOWN
Platform: UNKNOWN
Classifier: Programming Language :: Python :: 3
Classifier: License :: OSI Approved :: MIT License
Classifier: Operating System :: OS Independent
